[
  {
    "name": "B치sico",
    "monthly": 49900,
    "yearly": 42400,
    "features": [
      "Sala de pesas ilimitada",
      "Rutina inicial + chequeo"
    ]
  },
  {
    "name": "Pro",
    "monthly": 74900,
    "yearly": 63700,
    "features": [
      "Todo del B치sico",
      "4 clases grupales/mes",
      "Evaluaci칩n mensual"
    ]
  },
  {
    "name": "Full",
    "monthly": 119900,
    "yearly": 101900,
    "features": [
      "Todo del Pro",
      "Plan nutricional",
      "Acompa침amiento 1:1"
    ]
  },
  {
    "name": "Estudiante",
    "monthly": 39900,
    "yearly": 33900,
    "features": [
      "Descuento especial",
      "Acceso total en horarios valle"
    ]
  }
]